pyqoiv/__init__.py
pyqoiv/cli.py
pyqoiv/decode.py
pyqoiv/encode.py
pyqoiv/opcodes.py
pyqoiv/types.py
pyqoiv-0.4.0.dist-info/COPYING
pyqoiv-0.4.0.dist-info/METADATA
pyqoiv-0.4.0.dist-info/WHEEL
pyqoiv-0.4.0.dist-info/entry_points.txt
pyqoiv-0.4.0.dist-info/RECORD
