Metadata-Version: 2.3
Name: pyqoiv
Version: 0.4.0
Summary: A python implementation of QOIV, an video format based on QOI
License: MIT
Author: Mark Goodall
Author-email: mark.goodall@gmail.com
Requires-Python: >=3.12,<4.0
Classifier: License :: OSI Approved :: MIT License
Classifier: Programming Language :: Python :: 3
Classifier: Programming Language :: Python :: 3.12
Classifier: Programming Language :: Python :: 3.13
Requires-Dist: ffmpeg-python (>=0.2.0,<0.3.0)
Requires-Dist: numpy (>=2.2.6,<3.0.0)
Requires-Dist: tqdm (>=4.67.1,<5.0.0)
Requires-Dist: typer (>=0.16.0,<0.17.0)
